rpyc_ws/__init__.py
rpyc_ws/client.py
rpyc_ws/server.py
rpyc_ws/stream.py
rpyc_ws-0.3.3.dist-info/METADATA
rpyc_ws-0.3.3.dist-info/WHEEL
rpyc_ws-0.3.3.dist-info/licenses/LICENSE
rpyc_ws-0.3.3.dist-info/RECORD
