Metadata-Version: 2.4
Name: rpyc-ws
Version: 0.3.3
Summary: RPyC over WebSocket
Author-email: Luke Cummings <luke.cummings@cenovus.com>
License-File: LICENSE
Requires-Python: >=3.9
Requires-Dist: fastapi>=0.115.12
Requires-Dist: rpyc>=6.0.2
Requires-Dist: websockets>=15.0.1
